_secp256k1_zkp_mw
secp256k1_zkp_mw
